hylexcrypt/__init__.py
hylexcrypt/_version.py
hylexcrypt/cli.py
hylexcrypt/core.py
hylexcrypt-2050.1.1.dist-info/METADATA
hylexcrypt-2050.1.1.dist-info/WHEEL
hylexcrypt-2050.1.1.dist-info/entry_points.txt
hylexcrypt-2050.1.1.dist-info/top_level.txt
hylexcrypt-2050.1.1.dist-info/RECORD
