Metadata-Version: 2.4
Name: HylexCrypt
Version: 2050.1.1
Summary: HylexCrypt - The Ultimate 2050 - stego + crypto CLI tool
Author-email: "Deepak P S , Nithin S" <deepakkrishnark@gmail.com>
Maintainer-email: TwinCiphers <twinciphers@gmail.com>
License: Apache-2.0
Project-URL: homepage, https://github.com/TwinCiphers/HylexCrypt-TU2050
Project-URL: documentation, https://hackmd.io/@hylexcrypt-tu2050/SkRnM51ogl
Project-URL: repository, https://github.com/TwinCiphers/HylexCrypt-TU2050
Project-URL: bug_tracker, https://github.com/TwinCiphers/HylexCrypt-TU2050/issues
Project-URL: changelog, https://github.com/TwinCiphers/HylexCrypt-TU2050/blob/main/changelog.md
Keywords: steganography,cryptography,security,encryption,LSB,image-processing,audio-processing,argon2,chacha20
Classifier: Development Status :: 5 - Production/Stable
Classifier: Environment :: Console
Classifier: Intended Audience :: Developers
Classifier: Intended Audience :: Information Technology
Classifier: Intended Audience :: System Administrators
Classifier: License :: OSI Approved :: Apache Software License
Classifier: Operating System :: OS Independent
Classifier: Programming Language :: Python :: 3
Classifier: Programming Language :: Python :: 3.9
Classifier: Programming Language :: Python :: 3.10
Classifier: Programming Language :: Python :: 3.11
Classifier: Topic :: Security :: Cryptography
Classifier: Topic :: Security
Classifier: Topic :: Software Development :: Libraries :: Python Modules
Classifier: Topic :: System :: Archiving
Classifier: Topic :: Utilities
Requires-Python: >=3.9
Requires-Dist: numpy>=1.21.0
Requires-Dist: Pillow>=9.0.0
Requires-Dist: cryptography>=40.0.0
Requires-Dist: argon2-cffi>=21.0.0
Provides-Extra: dct
Requires-Dist: scipy; extra == "dct"
Provides-Extra: fec
Requires-Dist: reedsolo; extra == "fec"
Provides-Extra: audio
Requires-Dist: soundfile; extra == "audio"
Provides-Extra: ui
Requires-Dist: colorama; extra == "ui"
Provides-Extra: monitor
Requires-Dist: psutil; extra == "monitor"
